boj2md/__init__.py
boj2md-0.0.2.dist-info/LICENSE
boj2md-0.0.2.dist-info/METADATA
boj2md-0.0.2.dist-info/WHEEL
boj2md-0.0.2.dist-info/entry_points.txt
boj2md-0.0.2.dist-info/top_level.txt
boj2md-0.0.2.dist-info/RECORD
